{
  "Title": "OpenHack - Migrating Microsoft Workloads to Azure ZH",
  "Description" : "OpenHack challenges for Migrating Microsoft Workloads to Azure",
  "OverviewUrl" : "Overview.html",
  "ContentVersion": "3.1",
  "ContentPackage": {
    "ContentItems": [
      {
        "Order": 1,
        "Title": "Challenge 1: Establish your plan",
        "Description": "Establish your plan.",
        "Url": "Challenge-1.html"
      },
      {
        "Order": 2,
        "Follows": 1,
        "Title": "Challenge 2: Assess workloads for migration",
        "Description": "Plan the migration of on-premises workloads to Azure.",
        "Url": "Challenge-2.html"
      },
      {
        "Order": 3,
        "Follows": 2,
        "Title": "Challenge 3: Implement hybrid identity",
        "Description": "Plan the migration of on-premises identities to Azure Active Directory.",
        "Url": "Challenge-3.html"
      },
      {
        "Order": 4,
        "Follows": 3,
        "Title": "Challenge 4: Implement hybrid networking and resilient authentication",
        "Description": "Implement site-to-site connectivity between on-premises and Azure and establish resilient authentication.",
        "Url": "Challenge-4.html"
      },
      {
        "Order": 5,
        "Follows": 4,
        "Title": "Challenge 5: Test migration",
        "Description": "Migrate the on-premises workloads to Azure in a phased manner for testing.",
        "Url": "Challenge-5.html"
      },
      {
        "Order": 6,
        "Follows": 5,
        "Title": "Challenge 6: Finalize migration",
        "Description": "Migrate the on-premises workloads to Azure and complete the migration.",
        "Url": "Challenge-6.html"
      },
      {
        "Order": 7,
        "Follows": 6,
        "Title": "Challenge 7: Transition to platform database services",
        "Description": "Migrate a database backend from MS SQL Server to platform database services.",
        "Url": "Challenge-7.html"
      },
      {
        "Order": 8,
        "Follows": 7,
        "Title": "Challenge 8: Transition to platform web-hosting services",
        "Description": "Migrate exiting websites from IaaS to PaaS with platform web-hosting services.",
        "Url": "Challenge-8.html"
      },
      {
        "Order": 9,
        "Follows": 8,
        "Title": "Challenge 9: Secure, optimize, and operate",
        "Description": "Optimize an existing environment through the implementation of additional security controls and monitoring.",
        "Url": "Challenge-9.html"
      }
    ]
  }
}